wagtail_ab_testing/__init__.py
wagtail_ab_testing/api.py
wagtail_ab_testing/apps.py
wagtail_ab_testing/compat.py
wagtail_ab_testing/events.py
wagtail_ab_testing/models.py
wagtail_ab_testing/urls.py
wagtail_ab_testing/utils.py
wagtail_ab_testing/views.py
wagtail_ab_testing/wagtail_hooks.py
wagtail_ab_testing/migrations/0001_initial.py
wagtail_ab_testing/migrations/0001_squashed_0012_abtest_variant_revision.py
wagtail_ab_testing/migrations/0002_abtesthourlylog.py
wagtail_ab_testing/migrations/0003_abtest_winning_variant.py
wagtail_ab_testing/migrations/0004_started_at_and_duration.py
wagtail_ab_testing/migrations/0005_hypothesis_and_created_by.py
wagtail_ab_testing/migrations/0006_sample_size_min_value.py
wagtail_ab_testing/migrations/0007_grant_moderators_add_abtest_permission.py
wagtail_ab_testing/migrations/0008_finished_status.py
wagtail_ab_testing/migrations/0009_rename_variant_to_version.py
wagtail_ab_testing/migrations/0010_rename_treatment_to_variant.py
wagtail_ab_testing/migrations/0011_rename_treatment_to_variant_data.py
wagtail_ab_testing/migrations/0012_abtest_variant_revision.py
wagtail_ab_testing/migrations/0013_alter_abtest_variant_revision.py
wagtail_ab_testing/migrations/__init__.py
wagtail_ab_testing/static/wagtail_ab_testing/js/tracker.js
wagtail_ab_testing/static/wagtail_ab_testing/js/wagtail-ab-testing.js
wagtail_ab_testing/static/wagtail_ab_testing/js/wagtail-ab-testing.js.LICENSE.txt
wagtail_ab_testing/templates/wagtail_ab_testing/add_compare.html
wagtail_ab_testing/templates/wagtail_ab_testing/add_form.html
wagtail_ab_testing/templates/wagtail_ab_testing/compare.html
wagtail_ab_testing/templates/wagtail_ab_testing/delete_ab_tests.html
wagtail_ab_testing/templates/wagtail_ab_testing/progress.html
wagtail_ab_testing/templates/wagtail_ab_testing/report.html
wagtail_ab_testing/templates/wagtail_ab_testing/results.html
wagtail_ab_testing/templates/wagtail_ab_testing/script.html
wagtail_ab_testing/templates/wagtail_ab_testing/_compat/report.html
wagtail_ab_testing-0.12.dist-info/licenses/LICENSE
wagtail_ab_testing-0.12.dist-info/METADATA
wagtail_ab_testing-0.12.dist-info/WHEEL
wagtail_ab_testing-0.12.dist-info/top_level.txt
wagtail_ab_testing-0.12.dist-info/RECORD
