Metadata-Version: 2.4
Name: wagtail-ab-testing
Version: 0.12
Summary: A/B Testing for Wagtail
Author-email: Wagtail Nest team <hello@wagtail.org>
Project-URL: Changelog, https://github.com/wagtail-nest/wagtail-ab-testing/blob/main/CHANGELOG.md
Project-URL: Homepage, https://github.com/wagtail-nest/wagtail-ab-testing/
Project-URL: Issue tracker, https://github.com/wagtail-nest/wagtail-ab-testing/issues/
Project-URL: Source, https://github.com/wagtail-nest/wagtail-ab-testing/
Classifier: Development Status :: 3 - Alpha
Classifier: Framework :: Django
Classifier: Framework :: Django :: 4.2
Classifier: Framework :: Django :: 5.0
Classifier: Framework :: Django :: 5.1
Classifier: Framework :: Django :: 5.2
Classifier: Framework :: Wagtail
Classifier: Framework :: Wagtail :: 5
Classifier: Framework :: Wagtail :: 6
Classifier: Framework :: Wagtail :: 7
Classifier: Intended Audience :: Developers
Classifier: License :: OSI Approved :: BSD License
Classifier: Operating System :: OS Independent
Classifier: Programming Language :: Python
Classifier: Programming Language :: Python :: 3
Classifier: Programming Language :: Python :: 3.9
Classifier: Programming Language :: Python :: 3.10
Classifier: Programming Language :: Python :: 3.11
Classifier: Programming Language :: Python :: 3.12
Classifier: Programming Language :: Python :: 3.13
License-File: LICENSE
Requires-Dist: numpy<2,>=1.19.4
Requires-Dist: scipy<2,>=1.5.4
Requires-Dist: user-agents<2.3,>=2.2
Requires-Dist: Wagtail>=5.2
Provides-Extra: testing
Requires-Dist: coverage[toml]<8.0,>=7.2.7; extra == "testing"
Requires-Dist: dj-database-url==2.3.0; extra == "testing"
Requires-Dist: freezegun==1.5.1; extra == "testing"
Requires-Dist: pre-commit>=3.4.0; extra == "testing"
Dynamic: license-file
